README.rst
setup.py
dummipy/__init__.py
dummipy/dummipy.py
dummipy/test.py
dummipy.egg-info/PKG-INFO
dummipy.egg-info/SOURCES.txt
dummipy.egg-info/dependency_links.txt
dummipy.egg-info/not-zip-safe
dummipy.egg-info/requires.txt
dummipy.egg-info/top_level.txt
dummipy/data/cereal.csv